i6_rsync/__init__.py
i6_rsync/rsync.py
i6_rsync-2.0.1.dist-info/METADATA
i6_rsync-2.0.1.dist-info/WHEEL
i6_rsync-2.0.1.dist-info/licenses/LICENSE
i6_rsync-2.0.1.dist-info/RECORD
