Metadata-Version: 2.4
Name: i6_rsync
Version: 2.0.1
Summary: make rsync between local and remote directories easy and fast
Project-URL: Homepage, https://github.com/imahdimir/i6_rsync
Author-email: Mahdi Mir <imahdimir@gmail.com>
License: MIT License
License-File: LICENSE
Keywords: rsync
Requires-Dist: pyperclip==1.9.0
